{
  "totalContacts": 9966,
  "sources": {
    "wix": 405,
    "constant_contact": 7905,
    "both": 1656
  },
  "tags": [
    "Bolen",
    "Carol Pearson Salon Attendees",
    "Friends & Family",
    "Zoom",
    "handwritten"
  ],
  "emailLists": [
    "\"Read more\" clickers",
    "\"Watch Now\" Clickers",
    "'---",
    "'------",
    "---",
    "------",
    "BLM letter readers",
    "Calendar Clickers",
    "Dennis's list",
    "DennisPatrickSlattery.com",
    "Facebook Clickers",
    "Feb15",
    "Feminine",
    "Figure in Focus Clickers",
    "General Interest",
    "Holiday Clickers",
    "IG signups",
    "INF.POT.WATCHERS",
    "LV 2.0002 Clickers",
    "Link Click - MWP",
    "Link Click - ScreenCraft",
    "Link Clickers - CGood",
    "Link Clickers - Hollihock",
    "Link Clickers - Hussian",
    "Link Clickers - Mack Sennett",
    "Link Clickers - Mythosophia",
    "Literati JCF",
    "Lost in thought LEFT EYE clickers",
    "MWP clickers",
    "Myth Blasts",
    "Myth Salon - Friends & Family",
    "Myth Salon - Zoom emails",
    "Myth Salon Master email registration lists",
    "Myth Salon pre-Zoom",
    "Myth Salon/Mythosophia All",
    "Mythology Classroom",
    "Mythosophia new",
    "Mythouse Website",
    "Mythouse.org",
    "New Zoom Jan21 21",
    "Next week event clickers",
    "Opened 6/9/21",
    "Pacifica Clickers",
    "Screening",
    "Shoppers",
    "Story Atlas Website",
    "TRANSFORMATIONAL NARRATIVE",
    "Will",
    "Will clickers",
    "Wix - All Customers",
    "Wix - First time Customers",
    "Wix - Lapsed Customers",
    "Wix - Potential Customers",
    "Wix - Recent Customers",
    "Wix - Repeat Customers",
    "Writer's Journey 25th Anniversary Celebration Registrants",
    "Writer's Journey Celebration Attendees",
    "Writers' Journey Clickers",
    "Youtube clickers",
    "Zoom",
    "alchemyinc.net",
    "climate",
    "illuminate",
    "uploaded 7/23/21"
  ],
  "labels": [
    "Custom Signup Form",
    "Custom Signup Form;Customers",
    "Customers",
    "Demo Label"
  ],
  "emailStatuses": [
    "Never subscribed",
    "Subscribed"
  ],
  "ccEmailStatuses": [
    "Active",
    "No Permissions Set",
    "Unsubscribed"
  ],
  "ccPermissionStatuses": [
    "Express",
    "Implied"
  ],
  "countries": [
    "Argentina",
    "Australia",
    "Belarus",
    "Belgium",
    "Bermuda",
    "Brazil",
    "Bulgaria",
    "Canada",
    "Chile",
    "China",
    "Estonia",
    "Finland",
    "France",
    "Georgia",
    "Germany",
    "Guatemala",
    "Hong Kong SAR",
    "India",
    "Indonesia",
    "Ireland",
    "Israel",
    "Italy",
    "Japan",
    "Korea",
    "Korea, Republic of",
    "Lithuania",
    "Luxembourg",
    "Malaysia",
    "Mexico",
    "New Zealand",
    "Panama",
    "Philippines",
    "Poland",
    "Portugal",
    "Puerto Rico",
    "Romania",
    "Russian Federation",
    "Saudi Arabia",
    "Serbia",
    "South Africa",
    "Spain",
    "Sri Lanka",
    "Taiwan",
    "Thailand",
    "Trinidad And Tobago",
    "Turkey",
    "Ukraine",
    "United Arab Emirates",
    "United Kingdom",
    "United States",
    "United States of America",
    "Viet Nam"
  ]
}